temp_brijesh_consul/__init__.py
temp_brijesh_consul/consul.py
temp_brijesh_consul-1.0.0.dist-info/licenses/LICENSE
temp_brijesh_consul-1.0.0.dist-info/METADATA
temp_brijesh_consul-1.0.0.dist-info/WHEEL
temp_brijesh_consul-1.0.0.dist-info/top_level.txt
temp_brijesh_consul-1.0.0.dist-info/RECORD
