Metadata-Version: 2.4
Name: temp_brijesh_consul
Version: 1.0.0
Summary: A Python client library for HashiCorp Consul with both synchronous and asynchronous support
Author-email: Brijesh Turabit <brijesh.turabit@gmail.com>
Requires-Python: >=3.8
License-File: LICENSE
Requires-Dist: python-consul2==0.1.5
Dynamic: license-file
